YeetsMenu/__init__.py
YeetsMenu/menu.py
YeetsMenu/option.py
YeetsMenu/generics/__init__.py
YeetsMenu/generics/selectable.py
YeetsMenu/utils/__init__.py
YeetsMenu/utils/utils.py
YeetsMenu-0.0.12.dist-info/LICENSE
YeetsMenu-0.0.12.dist-info/METADATA
YeetsMenu-0.0.12.dist-info/WHEEL
YeetsMenu-0.0.12.dist-info/top_level.txt
YeetsMenu-0.0.12.dist-info/RECORD
