Metadata-Version: 2.1
Name: YeetsMenu
Version: 0.0.12
Summary: A colored menu builder
Home-page: https://github.com/pypa/sampleproject
Author: DestinyofYeet
Author-email: ole@uwuwhatsthis.de
Project-URL: Bug Tracker, https://github.com/pypa/sampleproject/issues
Classifier: Programming Language :: Python :: 3
Classifier: License :: OSI Approved :: MIT License
Classifier: Operating System :: OS Independent
Requires-Python: >=3.6
License-File: LICENSE
Requires-Dist: colorama
